{
  "input geometry": {
    "function space": "StructuredColumns",
    "grid": {
      "type": "regional",
      "nx": "1796",
      "ny": "2321",
      "dx": "1.0e3",
      "dy": "1.0e3",
      "lonlat(centre)": ["15.001164907304375", "63.50071790568658"],
      "projection": {
        "type": "lambert_conformal_conic",
        "latitude0": "63.0",
        "longitude0": "15.0",
        "radius": "6371000.0"
      },
      "y_numbering": "-1"
    },
    "partitioner": "checkerboard",
    "groups": [
      {
        "variables": ["air_temperature_2m", "elevs"],
        "levels": "1"
      }
    ],
    "halo": "0"
  },
  "output geometry": {
    "function space": "StructuredColumns",
    "grid": {
      "type": "regional",
      "nx": "719",
      "ny": "929",
      "dx": "2.5e3",
      "dy": "2.5e3",
      "lonlat(centre)": ["15.001164907304375", "63.50071790568658"],
      "projection": {
        "type": "lambert_conformal_conic",
        "latitude0": "63.0",
        "longitude0": "15.0",
        "radius": "6371000.0"
      },
      "y_numbering": "-1"
    },
    "partitioner": "checkerboard",
    "groups": [
      {
        "variables": ["air_temperature_2m", "elevs"],
        "levels": "1"
      }
    ],
    "halo": "0"
  },
  "states": [
    {
      "input": {
        "date": "2023-12-05T06:00:00Z",
        "variables": ["air_temperature_2m", "elevs"],
        "filepath": "background_hr"
      },
      "output": {
        "date": "2023-12-05T06:00:00Z",
        "variables": ["air_temperature_2m", "elevs"],
        "filepath": "background_lr"
      }
    },
    {
      "input": {
        "date": "2023-12-05T06:00:00Z",
        "variables": ["air_temperature_2m", "elevs"],
        "filepath": "member_hr_000001"
      },
      "output": {
        "date": "2023-12-05T06:00:00Z",
        "variables": ["air_temperature_2m", "elevs"],
        "filepath": "member_lr_000001"
      }
    },
    {
      "input": {
        "date": "2023-12-05T06:00:00Z",
        "variables": ["air_temperature_2m", "elevs"],
        "filepath": "member_hr_000002"
      },
      "output": {
        "date": "2023-12-05T06:00:00Z",
        "variables": ["air_temperature_2m", "elevs"],
        "filepath": "member_lr_000002"
      }
    },
    {
      "input": {
        "date": "2023-12-05T06:00:00Z",
        "variables": ["air_temperature_2m", "elevs"],
        "filepath": "member_hr_000003"
      },
      "output": {
        "date": "2023-12-05T06:00:00Z",
        "variables": ["air_temperature_2m", "elevs"],
        "filepath": "member_lr_000003"
      }
    },
    {
      "input": {
        "date": "2023-12-05T06:00:00Z",
        "variables": ["air_temperature_2m", "elevs"],
        "filepath": "member_hr_000004"
      },
      "output": {
        "date": "2023-12-05T06:00:00Z",
        "variables": ["air_temperature_2m", "elevs"],
        "filepath": "member_lr_000004"
      }
    },
    {
      "input": {
        "date": "2023-12-05T06:00:00Z",
        "variables": ["air_temperature_2m", "elevs"],
        "filepath": "member_hr_000005"
      },
      "output": {
        "date": "2023-12-05T06:00:00Z",
        "variables": ["air_temperature_2m", "elevs"],
        "filepath": "member_lr_000005"
      }
    },
    {
      "input": {
        "date": "2023-12-05T06:00:00Z",
        "variables": ["air_temperature_2m", "elevs"],
        "filepath": "member_hr_000006"
      },
      "output": {
        "date": "2023-12-05T06:00:00Z",
        "variables": ["air_temperature_2m", "elevs"],
        "filepath": "member_lr_000006"
      }
    },
    {
      "input": {
        "date": "2023-12-05T06:00:00Z",
        "variables": ["air_temperature_2m", "elevs"],
        "filepath": "member_hr_000007"
      },
      "output": {
        "date": "2023-12-05T06:00:00Z",
        "variables": ["air_temperature_2m", "elevs"],
        "filepath": "member_lr_000007"
      }
    },
    {
      "input": {
        "date": "2023-12-05T06:00:00Z",
        "variables": ["air_temperature_2m", "elevs"],
        "filepath": "member_hr_000008"
      },
      "output": {
        "date": "2023-12-05T06:00:00Z",
        "variables": ["air_temperature_2m", "elevs"],
        "filepath": "member_lr_000008"
      }
    },
    {
      "input": {
        "date": "2023-12-05T06:00:00Z",
        "variables": ["air_temperature_2m", "elevs"],
        "filepath": "member_hr_000009"
      },
      "output": {
        "date": "2023-12-05T06:00:00Z",
        "variables": ["air_temperature_2m", "elevs"],
        "filepath": "member_lr_000009"
      }
    },
    {
      "input": {
        "date": "2023-12-05T06:00:00Z",
        "variables": ["air_temperature_2m", "elevs"],
        "filepath": "member_hr_000010"
      },
      "output": {
        "date": "2023-12-05T06:00:00Z",
        "variables": ["air_temperature_2m", "elevs"],
        "filepath": "member_lr_000010"
      }
    },
    {
      "input": {
        "date": "2023-12-05T06:00:00Z",
        "variables": ["air_temperature_2m", "elevs"],
        "filepath": "member_hr_000011"
      },
      "output": {
        "date": "2023-12-05T06:00:00Z",
        "variables": ["air_temperature_2m", "elevs"],
        "filepath": "member_lr_000011"
      }
    },
    {
      "input": {
        "date": "2023-12-05T06:00:00Z",
        "variables": ["air_temperature_2m", "elevs"],
        "filepath": "member_hr_000012"
      },
      "output": {
        "date": "2023-12-05T06:00:00Z",
        "variables": ["air_temperature_2m", "elevs"],
        "filepath": "member_lr_000012"
      }
    },
    {
      "input": {
        "date": "2023-12-05T06:00:00Z",
        "variables": ["air_temperature_2m", "elevs"],
        "filepath": "member_hr_000013"
      },
      "output": {
        "date": "2023-12-05T06:00:00Z",
        "variables": ["air_temperature_2m", "elevs"],
        "filepath": "member_lr_000013"
      }
    },
    {
      "input": {
        "date": "2023-12-05T06:00:00Z",
        "variables": ["air_temperature_2m", "elevs"],
        "filepath": "member_hr_000014"
      },
      "output": {
        "date": "2023-12-05T06:00:00Z",
        "variables": ["air_temperature_2m", "elevs"],
        "filepath": "member_lr_000014"
      }
    },
    {
      "input": {
        "date": "2023-12-05T06:00:00Z",
        "variables": ["air_temperature_2m", "elevs"],
        "filepath": "member_hr_000015"
      },
      "output": {
        "date": "2023-12-05T06:00:00Z",
        "variables": ["air_temperature_2m", "elevs"],
        "filepath": "member_lr_000015"
      }
    }
  ]
}
